sdk_entrepot_gpf/Errors.py
sdk_entrepot_gpf/__init__.py
sdk_entrepot_gpf/__main__.py
sdk_entrepot_gpf/py.typed
sdk_entrepot_gpf/_conf/default.ini
sdk_entrepot_gpf/_conf/json_schemas/annexe_descriptor_file.json
sdk_entrepot_gpf/_conf/json_schemas/metadata_descriptor_file.json
sdk_entrepot_gpf/_conf/json_schemas/static_descriptor_file.json
sdk_entrepot_gpf/_conf/json_schemas/upload_descriptor_file.json
sdk_entrepot_gpf/_conf/json_schemas/workflow.json
sdk_entrepot_gpf/_data/datasets/1_dataset_vector/CANTON.md5
sdk_entrepot_gpf/_data/datasets/1_dataset_vector/CANTON_style.sld
sdk_entrepot_gpf/_data/datasets/1_dataset_vector/upload_descriptor.json
sdk_entrepot_gpf/_data/datasets/1_dataset_vector/CANTON/CANTON.cpg
sdk_entrepot_gpf/_data/datasets/1_dataset_vector/CANTON/CANTON.dbf
sdk_entrepot_gpf/_data/datasets/1_dataset_vector/CANTON/CANTON.prj
sdk_entrepot_gpf/_data/datasets/1_dataset_vector/CANTON/CANTON.shp
sdk_entrepot_gpf/_data/datasets/1_dataset_vector/CANTON/CANTON.shx
sdk_entrepot_gpf/_data/datasets/2_dataset_archive/CANTON.md5
sdk_entrepot_gpf/_data/datasets/2_dataset_archive/upload_descriptor.json
sdk_entrepot_gpf/_data/datasets/2_dataset_archive/CANTON/CANTON.zip
sdk_entrepot_gpf/_data/datasets/3_dataset_raster/ain.md5
sdk_entrepot_gpf/_data/datasets/3_dataset_raster/upload_descriptor.jsonc
sdk_entrepot_gpf/_data/datasets/3_dataset_raster/ain/01-2021-0920-6564-LA93-0M50-E100.tiff
sdk_entrepot_gpf/_data/datasets/3_dataset_raster/ain/01-2021-0920-6565-LA93-0M50-E100.tiff
sdk_entrepot_gpf/_data/datasets/3_dataset_raster/ain/01-2021-0921-6564-LA93-0M50-E100.tiff
sdk_entrepot_gpf/_data/datasets/3_dataset_raster/ain/01-2021-0921-6565-LA93-0M50-E100.tiff
sdk_entrepot_gpf/_data/datasets/5_dataset_maj_bd_gpf/installation.sld
sdk_entrepot_gpf/_data/datasets/5_dataset_maj_bd_gpf/upload_descriptor.json
sdk_entrepot_gpf/_data/datasets/5_dataset_maj_bd_gpf/lot_1/installation-init.sql
sdk_entrepot_gpf/_data/datasets/5_dataset_maj_bd_gpf/lot_2/installation.gpkg
sdk_entrepot_gpf-0.1.44.dist-info/entry_points.txt
sdk_entrepot_gpf-0.1.44.dist-info/licenses/LICENSE
sdk_entrepot_gpf-0.1.44.dist-info/WHEEL
sdk_entrepot_gpf-0.1.44.dist-info/METADATA
sdk_entrepot_gpf-0.1.44.dist-info/RECORD
