Metadata-Version: 2.4
Name: sdk_entrepot_gpf
Version: 0.1.44
Summary: SDK Python pour simplifier l'utilisation de l'API Entrepôt de la Géoplateforme.
Author-email: Valentin Sasyan <valentin.sasyan@ign.fr>
Requires-Python: >=3.8
Classifier: License :: OSI Approved :: MIT License
Classifier: Programming Language :: Python :: 3
Classifier: Programming Language :: Python :: 3.8
License-File: LICENSE
Requires-Dist: requests>=2.6
Requires-Dist: configparser
Requires-Dist: types-requests
Requires-Dist: jsonschema
Requires-Dist: jsonc-parser
Requires-Dist: toml
Requires-Dist: types-toml
Requires-Dist: python-dateutil
Requires-Dist: types-python-dateutil
Requires-Dist: pyotp
Requires-Dist: requests_toolbelt
Requires-Dist: tabulate
Requires-Dist: types-tabulate
Requires-Dist: shapely
Requires-Dist: mkdocs-material==9.* ; extra == "doc"
Requires-Dist: mkdocstrings[python] ; extra == "doc"
Requires-Dist: black<23 ; extra == "test"
Requires-Dist: pylint==2.17 ; extra == "test"
Requires-Dist: mypy==0.981 ; extra == "test"
Requires-Dist: requests_mock ; extra == "test"
Requires-Dist: coverage ; extra == "test"
Project-URL: Documentation, https://geoplateforme.github.io/sdk-entrepot/
Project-URL: Source, https://github.com/Geoplateforme/sdk_entrepot
Provides-Extra: doc
Provides-Extra: test
